MANIFEST.in
README.md
manage.py
pyproject.toml
setup.cfg
setup.py
baseapp_ai_langkit/__init__.py
baseapp_ai_langkit/apps.py
baseapp_ai_langkit/settings.py
baseapp_ai_langkit.egg-info/PKG-INFO
baseapp_ai_langkit.egg-info/SOURCES.txt
baseapp_ai_langkit.egg-info/dependency_links.txt
baseapp_ai_langkit.egg-info/requires.txt
baseapp_ai_langkit.egg-info/top_level.txt
baseapp_ai_langkit/base/__init__.py
baseapp_ai_langkit/base/apps.py
baseapp_ai_langkit/base/agents/__init__.py
baseapp_ai_langkit/base/agents/base_agent.py
baseapp_ai_langkit/base/agents/langgraph_agent.py
baseapp_ai_langkit/base/agents/tests/__init__.py
baseapp_ai_langkit/base/agents/tests/factories.py
baseapp_ai_langkit/base/agents/tests/test_agents.py
baseapp_ai_langkit/base/agents/tests/test_langgraph_agent.py
baseapp_ai_langkit/base/interfaces/__init__.py
baseapp_ai_langkit/base/interfaces/base_runner.py
baseapp_ai_langkit/base/interfaces/console.py
baseapp_ai_langkit/base/interfaces/exceptions.py
baseapp_ai_langkit/base/interfaces/llm_node.py
baseapp_ai_langkit/base/prompt_schemas/__init__.py
baseapp_ai_langkit/base/prompt_schemas/base_prompt_schema.py
baseapp_ai_langkit/base/prompt_schemas/tests/__init__.py
baseapp_ai_langkit/base/prompt_schemas/tests/factories.py
baseapp_ai_langkit/base/prompt_schemas/tests/test_base_pormpt_schema.py
baseapp_ai_langkit/base/tools/base_tool.py
baseapp_ai_langkit/base/tools/inline_tool.py
baseapp_ai_langkit/base/tools/tests/__init__.py
baseapp_ai_langkit/base/tools/tests/factories.py
baseapp_ai_langkit/base/tools/tests/test_default_tool.py
baseapp_ai_langkit/base/utils/model_admin_helper.py
baseapp_ai_langkit/base/workers/__init__.py
baseapp_ai_langkit/base/workers/base_worker.py
baseapp_ai_langkit/base/workers/messages_worker.py
baseapp_ai_langkit/base/workers/orchestrator_worker.py
baseapp_ai_langkit/base/workers/synthesizer_worker.py
baseapp_ai_langkit/base/workers/tests/__init__.py
baseapp_ai_langkit/base/workers/tests/test_messages_worker.py
baseapp_ai_langkit/base/workers/tests/test_orchestrator_worker.py
baseapp_ai_langkit/base/workers/tests/test_synthesizer_worker.py
baseapp_ai_langkit/base/workflows/__init__.py
baseapp_ai_langkit/base/workflows/base_workflow.py
