Metadata-Version: 2.4
Name: baseapp_ai_langkit
Version: 0.6.1
Summary: A Django app for LLM chat functionality with Langchain and Langgraph integration
Home-page: https://github.com/silverlogic/baseapp-ai-langkit
Author: The SilverLogic
Author-email: dev@tsl.io
License: BSD-3-Clause
Requires-Python: >=3.11
Requires-Dist: celery>=5.2
Requires-Dist: Django>=4.2
Requires-Dist: djangorestframework>=3.14
Requires-Dist: django-admin-sortable2>=2.2
Requires-Dist: django-constance[database]>=3.1
Requires-Dist: django-model-utils>=4.3
Requires-Dist: django-nested-admin>=4.1
Requires-Dist: django-pgtrigger>=4.12.2
Requires-Dist: django-extensions>=4.1
Requires-Dist: pydantic>=2.10
Requires-Dist: python-dotenv>=1.0.0
Requires-Dist: psycopg2-binary>=2.9
Provides-Extra: dev
Requires-Dist: factory-boy>=3.3.0; extra == "dev"
Requires-Dist: pytest>=7.0; extra == "dev"
Requires-Dist: pytest-django>=4.5.0; extra == "dev"
Requires-Dist: pytest-factoryboy>=2.5.0; extra == "dev"
Requires-Dist: black>=25.11.0; extra == "dev"
Requires-Dist: isort>=5.12; extra == "dev"
Requires-Dist: flake8>=6.0; extra == "dev"
Requires-Dist: responses>=0.25.0; extra == "dev"
Provides-Extra: langkit
Requires-Dist: langchain<1.0,>=0.3; extra == "langkit"
Requires-Dist: langchain-core>=0.3; extra == "langkit"
Requires-Dist: langchain-community>=0.3; extra == "langkit"
Requires-Dist: langchain-openai>=0.3; extra == "langkit"
Requires-Dist: langchain-postgres>=0.0; extra == "langkit"
Requires-Dist: langgraph<1.0,>=0.5; extra == "langkit"
Requires-Dist: langgraph-checkpoint-postgres<2.1,>=2.0.21; extra == "langkit"
Requires-Dist: pygments>=2.19; extra == "langkit"
Requires-Dist: slack-sdk>=3.35; extra == "langkit"
Requires-Dist: pydash>=8.0.5; extra == "langkit"
Requires-Dist: beautifulsoup4>=4.13.4; extra == "langkit"
Provides-Extra: mcp
Requires-Dist: mcp>=1.13.1; extra == "mcp"
Requires-Dist: fastmcp>=2.12.0; extra == "mcp"
Requires-Dist: anyio>=3.0.0; extra == "mcp"
Requires-Dist: uvicorn>=0.20.0; extra == "mcp"
Requires-Dist: langchain<1.0,>=0.3; extra == "mcp"
Dynamic: description
Dynamic: description-content-type
